pyJunosManager/__init__.py
pyJunosManager/exceptions.py
pyJunosManager/pyJunosManager.py
pyJunosManager/version.py
pyJunosManager-0.6.dist-info/DESCRIPTION.rst
pyJunosManager-0.6.dist-info/METADATA
pyJunosManager-0.6.dist-info/metadata.json
pyJunosManager-0.6.dist-info/RECORD
pyJunosManager-0.6.dist-info/top_level.txt
pyJunosManager-0.6.dist-info/WHEEL
