Metadata-Version: 2.0
Name: pyJunosManager
Version: 0.6
Summary: A simplified module to handle common Junos tasks
Home-page: https://github.com/JNPRAutomate/pyJunosManager
Author: Rob Cameron
Author-email: rcameron@juniper.net
License: Apache 2.0
Platform: UNKNOWN
Classifier: License :: OSI Approved :: Apache Software License
Classifier: Operating System :: OS Independent
Classifier: Programming Language :: Python
Classifier: Development Status :: 3 - Alpha
Classifier: Environment :: Console
Classifier: Programming Language :: Python :: 2.7
Requires-Dist: junos-eznc (>=1.0.2)
Requires-Dist: Jinja2 (>=2.7.3)
